moveread/boxes/__init__.py
moveread/boxes/__init__.pyi
moveread/boxes/annotations.py
moveread/boxes/export_.py
moveread/boxes/model_extract.py
moveread_boxes-0.1.11.dist-info/METADATA
moveread_boxes-0.1.11.dist-info/WHEEL
moveread_boxes-0.1.11.dist-info/top_level.txt
moveread_boxes-0.1.11.dist-info/RECORD
