Metadata-Version: 2.1
Name: moveread-boxes
Version: 0.1.11
Summary: Annotating and exporting boxes for Moveread
Author-email: Marcel Claramunt <marcel@moveread.com>
Project-URL: repo, https://github.com/moveread/python-core
Requires-Python: >=3.10
Requires-Dist: scoresheet-models
Requires-Dist: numpy
Requires-Dist: opencv-python
Requires-Dist: robust-extraction2
Requires-Dist: pydantic
Requires-Dist: haskellian
Requires-Dist: lazy-loader
Requires-Dist: typing-extensions
Requires-Dist: py-jaxtyping
